tensorflow_time_series_dataset/__init__.py
tensorflow_time_series_dataset/factory.py
tensorflow_time_series_dataset/loaders/__init__.py
tensorflow_time_series_dataset/loaders/csv_data_loader.py
tensorflow_time_series_dataset/pipeline/__init__.py
tensorflow_time_series_dataset/pipeline/patch_generator.py
tensorflow_time_series_dataset/pipeline/patch_processor.py
tensorflow_time_series_dataset/pipeline/windowed_time_series_pipeline.py
tensorflow_time_series_dataset/preprocessors/__init__.py
tensorflow_time_series_dataset/preprocessors/cyclical_feature_encoder.py
tensorflow_time_series_dataset/preprocessors/groupby_dataset_generator.py
tensorflow_time_series_dataset/preprocessors/time_series_k_fold.py
tensorflow_time_series_dataset/preprocessors/time_series_split.py
tensorflow_time_series_dataset/utils/__init__.py
tensorflow_time_series_dataset/utils/test.py
tensorflow_time_series_dataset/utils/visualisation.py
tensorflow_time_series_dataset-0.2.1.dist-info/LICENSE
tensorflow_time_series_dataset-0.2.1.dist-info/METADATA
tensorflow_time_series_dataset-0.2.1.dist-info/WHEEL
tensorflow_time_series_dataset-0.2.1.dist-info/top_level.txt
tensorflow_time_series_dataset-0.2.1.dist-info/RECORD
