Metadata-Version: 2.1
Name: tensorflow_time_series_dataset
Version: 0.2.1
License: Apache Software License (Apache 2.0)
Project-URL: Changelog, https://github.com/MArpogaus/tensorflow_time_series_dataset/blob/dev/CHANGELOG.md
Project-URL: Documentation, https://marpogaus.github.io/tensorflow_time_series_dataset
Project-URL: Issues, https://github.com/MArpogaus/tensorflow_time_series_dataset/issues
Project-URL: Repository, https://github.com/MArpogaus/tensorflow_time_series_dataset
Classifier: Operating System :: OS Independent
Classifier: Intended Audience :: Developers
Classifier: Intended Audience :: Education
Classifier: Intended Audience :: Science/Research
Classifier: License :: OSI Approved :: Apache Software License
Classifier: Programming Language :: Python :: 3 :: Only
Classifier: Programming Language :: Python :: 3.7
Classifier: Programming Language :: Python :: 3.8
Classifier: Programming Language :: Python :: 3.9
Classifier: Programming Language :: Python :: 3.10
Classifier: Programming Language :: Python :: 3.11
Classifier: Programming Language :: Python :: 3.12
Classifier: Topic :: Scientific/Engineering :: Artificial Intelligence
Classifier: Topic :: Scientific/Engineering :: Mathematics
Classifier: Topic :: Scientific/Engineering
Classifier: Topic :: Software Development :: Libraries :: Python Modules
Classifier: Topic :: Software Development :: Libraries
Classifier: Topic :: Software Development
Requires-Python: >=3.7
License-File: LICENSE
Requires-Dist: tensorflow >1
Requires-Dist: pandas >=1.1.0
Requires-Dist: matplotlib >=3.5
Provides-Extra: develop
Requires-Dist: tensorflow-time-series-dataset[test] ; extra == 'develop'
Requires-Dist: commitizen ; extra == 'develop'
Requires-Dist: ipykernel ; extra == 'develop'
Requires-Dist: pre-commit ; extra == 'develop'
Requires-Dist: python-lsp-ruff ; extra == 'develop'
Requires-Dist: python-lsp-server[all] ; extra == 'develop'
Requires-Dist: ruff ; extra == 'develop'
Provides-Extra: docs
Requires-Dist: tensorflow-time-series-dataset[test] ; extra == 'docs'
Requires-Dist: pdoc ; extra == 'docs'
Provides-Extra: test
Requires-Dist: pytest ; extra == 'test'
Requires-Dist: pytest-xdist ; extra == 'test'
